gre/__init__.py
gre/main.py
gre/vocab.py
gre-0.1.5.dist-info/LICENSE
gre-0.1.5.dist-info/METADATA
gre-0.1.5.dist-info/WHEEL
gre-0.1.5.dist-info/entry_points.txt
gre-0.1.5.dist-info/top_level.txt
gre-0.1.5.dist-info/RECORD
