Metadata-Version: 2.1
Name: gre
Version: 0.1.5
Summary: A handy helper to manage GRE Vocab preparation
Home-page: https://github.com/Sayan98/gre
Author: Sayan Goswami
Author-email: <goswami.sayan47@gmail.com>
License: MIT
Platform: UNKNOWN
Classifier: License :: OSI Approved :: MIT License
Classifier: Programming Language :: Python :: 3
Classifier: Programming Language :: Python :: 3.7
Requires-Dist: Click
Requires-Dist: tinydb
Requires-Dist: wiktionaryparser
